_kaldi_decoder.cpython-314-aarch64-linux-gnu.so
kaldi_decoder/__init__.py
kaldi_decoder-0.2.11.dist-info/METADATA
kaldi_decoder-0.2.11.dist-info/WHEEL
kaldi_decoder-0.2.11.dist-info/top_level.txt
kaldi_decoder-0.2.11.dist-info/RECORD
kaldi_decoder-0.2.11.dist-info/licenses/LICENSE
