Metadata-Version: 2.4
Name: kaldi-decoder
Version: 0.2.11
Home-page: https://github.com/k2-fsa/kaldi-decoder
Author: The next-gen Kaldi development team
Author-email: csukuangfj@gmail.com
License: Apache-2.0
Classifier: Programming Language :: C++
Classifier: Programming Language :: Python
Classifier: Topic :: Scientific/Engineering :: Artificial Intelligence
Requires-Python: >=3.8
License-File: LICENSE
Dynamic: author
Dynamic: author-email
Dynamic: classifier
Dynamic: description
Dynamic: description-content-type
Dynamic: home-page
Dynamic: license
Dynamic: license-file
Dynamic: requires-python
